dvas/__init__.py
dvas/dvas.py
dvas/dynamic.py
dvas/environ.py
dvas/errors.py
dvas/hardcoded.py
dvas/helper.py
dvas/logger.py
dvas/version.py
dvas/config/__init__.py
dvas/config/config.py
dvas/config/definitions/__init__.py
dvas/config/definitions/csvorigmeta.py
dvas/config/definitions/flg.py
dvas/config/definitions/model.py
dvas/config/definitions/origdata.py
dvas/config/definitions/prm.py
dvas/config/definitions/tag.py
dvas/data/__init__.py
dvas/data/data.py
dvas/data/io.py
dvas/data/linker.py
dvas/data/strategy/__init__.py
dvas/data/strategy/data.py
dvas/data/strategy/load.py
dvas/data/strategy/plot.py
dvas/data/strategy/rebase.py
dvas/data/strategy/resample.py
dvas/data/strategy/save.py
dvas/data/strategy/sort.py
dvas/database/__init__.py
dvas/database/database.py
dvas/database/explorer.py
dvas/database/model.py
dvas/database/search.py
dvas/plots/__init__.py
dvas/plots/dtas.py
dvas/plots/gdps.py
dvas/plots/plots.py
dvas/plots/utils.py
dvas/plots/mpl_styles/base.mplstyle
dvas/plots/mpl_styles/latex.mplstyle
dvas/plots/mpl_styles/nolatex.mplstyle
dvas/tools/__init__.py
dvas/tools/chunks.py
dvas/tools/math.py
dvas/tools/sync.py
dvas/tools/tools.py
dvas/tools/wmo.py
dvas/tools/dtas/__init__.py
dvas/tools/dtas/dtas.py
dvas/tools/gdps/__init__.py
dvas/tools/gdps/correlations.py
dvas/tools/gdps/gdps.py
dvas/tools/gdps/stats.py
dvas_recipes/__init__.py
dvas_recipes/__main__.py
dvas_recipes/dynamic.py
dvas_recipes/errors.py
dvas_recipes/hl_commands.py
dvas_recipes/recipe.py
dvas_recipes/utils.py
dvas_recipes/configs/flg_config.yml
dvas_recipes/configs/prm_config.yml
dvas_recipes/configs/data_config/ATMS-3710_origdata.yml
dvas_recipes/configs/data_config/CF-06-AH_origdata.yml
dvas_recipes/configs/data_config/DFM-17_origdata.yml
dvas_recipes/configs/data_config/GTH3_origdata.yml
dvas_recipes/configs/data_config/M10_origdata.yml
dvas_recipes/configs/data_config/M20_origdata.yml
dvas_recipes/configs/data_config/PS-B3_origdata.yml
dvas-1.2.1.dist-info/AUTHORS
dvas-1.2.1.dist-info/LICENSE
dvas-1.2.1.dist-info/METADATA
dvas-1.2.1.dist-info/WHEEL
dvas-1.2.1.dist-info/entry_points.txt
dvas-1.2.1.dist-info/top_level.txt
dvas-1.2.1.dist-info/RECORD
